{"nodes": [{"id": "pipeline", "label": "pipeline.ts", "file_type": "code", "source_file": "server\\routes\\pipeline.ts", "source_location": "L1"}], "edges": [{"source": "pipeline", "target": "express", "relation": "imports_from", "confidence": "EXTRACTED", "source_file": "server\\routes\\pipeline.ts", "source_location": "L1", "weight": 1.0}, {"source": "pipeline", "target": "zod", "relation": "imports_from", "confidence": "EXTRACTED", "source_file": "server\\routes\\pipeline.ts", "source_location": "L2", "weight": 1.0}, {"source": "pipeline", "target": "schema", "relation": "imports_from", "confidence": "EXTRACTED", "source_file": "server\\routes\\pipeline.ts", "source_location": "L3", "weight": 1.0}, {"source": "pipeline", "target": "db", "relation": "imports_from", "confidence": "EXTRACTED", "source_file": "server\\routes\\pipeline.ts", "source_location": "L4", "weight": 1.0}, {"source": "pipeline", "target": "storage", "relation": "imports_from", "confidence": "EXTRACTED", "source_file": "server\\routes\\pipeline.ts", "source_location": "L5", "weight": 1.0}, {"source": "pipeline", "target": "pipeline", "relation": "imports_from", "confidence": "EXTRACTED", "source_file": "server\\routes\\pipeline.ts", "source_location": "L6", "weight": 1.0}, {"source": "pipeline", "target": "auth", "relation": "imports_from", "confidence": "EXTRACTED", "source_file": "server\\routes\\pipeline.ts", "source_location": "L13", "weight": 1.0}, {"source": "pipeline", "target": "drizzle_orm", "relation": "imports_from", "confidence": "EXTRACTED", "source_file": "server\\routes\\pipeline.ts", "source_location": "L14", "weight": 1.0}]}